{"matches": [{"unique_id": 1140385, "team-2": "England", "team-1": "Sri Lanka", "type": "Test", "date": "2018-11-06T00:00:00.000Z", "dateTimeGMT": "2018-11-06T04:30:00.000Z", "squad": true, "toss_winner_team": "England", "matchStarted": true}, {"unique_id": 1150533, "date": "2018-11-09T00:00:00.000Z", "dateTimeGMT": "2018-11-09T15:00:00.000Z", "team-1": "India Women", "team-2": "New Zealand Women", "type": "WomensT20I", "squad": true, "matchStarted": false}, {"unique_id": 1150534, "date": "2018-11-09T00:00:00.000Z", "dateTimeGMT": "2018-11-09T20:00:00.000Z", "team-1": "Australia Women", "team-2": "Pakistan Women", "type": "WomensT20I", "squad": true, "matchStarted": false}, {"unique_id": 1157379, "date": "2018-11-09T00:00:00.000Z", "dateTimeGMT": "2018-11-09T11:00:00.000Z", "team-1": "New Zealand", "team-2": "Pakistan", "type": "ODI", "squad": true, "matchStarted": false}, {"unique_id": 1144987, "date": "2018-11-09T00:00:00.000Z", "dateTimeGMT": "2018-11-09T03:20:00.000Z", "team-1": "Australia", "team-2": "South Africa", "type": "ODI", "squad": true, "matchStarted": false}, {"unique_id": 1150535, "date": "2018-11-10T00:00:00.000Z", "dateTimeGMT": "2018-11-10T00:00:00.000Z", "team-1": "West Indies Women", "team-2": "Bangladesh Women", "type": "WomensT20I", "squad": true, "matchStarted": false}, {"unique_id": 1150536, "date": "2018-11-10T00:00:00.000Z", "dateTimeGMT": "2018-11-10T20:00:00.000Z", "team-1": "England Women", "team-2": "Sri Lanka Women", "type": "WomensT20I", "squad": true, "matchStarted": false}, {"unique_id": 1157761, "team-2": "West Indies", "team-1": "India", "type": "T20I", "date": "2018-11-11T00:00:00.000Z", "dateTimeGMT": "2018-11-11T13:30:00.000Z", "squad": true, "matchStarted": false}, {"unique_id": 1153640, "date": "2018-11-11T00:00:00.000Z", "dateTimeGMT": "2018-11-11T03:30:00.000Z", "team-1": "Bangladesh", "team-2": "Zimbabwe", "type": "Test", "squad": true, "matchStarted": false}, {"unique_id": 1150537, "date": "2018-11-11T00:00:00.000Z", "dateTimeGMT": "2018-11-11T15:00:00.000Z", "team-1": "India Women", "team-2": "Pakistan Women", "type": "WomensT20I", "squad": true, "matchStarted": false}, {"unique_id": 1150538, "date": "2018-11-11T00:00:00.000Z", "dateTimeGMT": "2018-11-11T20:00:00.000Z", "team-1": "Australia Women", "team-2": "Ireland Women", "type": "WomensT20I", "squad": true, "matchStarted": false}, {"unique_id": 1157380, "date": "2018-11-11T00:00:00.000Z", "dateTimeGMT": "2018-11-11T11:00:00.000Z", "team-1": "New Zealand", "team-2": "Pakistan", "type": "ODI", "squad": true, "matchStarted": false}, {"unique_id": 1144988, "date": "2018-11-11T00:00:00.000Z", "dateTimeGMT": "2018-11-11T02:50:00.000Z", "team-1": "Australia", "team-2": "South Africa", "type": "ODI", "squad": true, "matchStarted": false}, {"unique_id": 1150539, "date": "2018-11-12T00:00:00.000Z", "dateTimeGMT": "2018-11-12T20:00:00.000Z", "team-1": "Bangladesh Women", "team-2": "England Women", "type": "WomensT20I", "squad": true, "matchStarted": false}, {"unique_id": 1150540, "date": "2018-11-13T00:00:00.000Z", "dateTimeGMT": "2018-11-13T00:00:00.000Z", "team-1": "South Africa Women", "team-2": "Sri Lanka Women", "type": "WomensT20I", "squad": true, "matchStarted": false}, {"unique_id": 1150541, "date": "2018-11-13T00:00:00.000Z", "dateTimeGMT": "2018-11-13T20:00:00.000Z", "team-1": "Ireland Women", "team-2": "Pakistan Women", "type": "WomensT20I", "squad": true, "matchStarted": false}, {"unique_id": 1140386, "team-2": "England", "team-1": "Sri Lanka", "type": "Test", "date": "2018-11-14T00:00:00.000Z", "dateTimeGMT": "2018-11-14T04:30:00.000Z", "squad": true, "matchStarted": false}, {"unique_id": 1150542, "date": "2018-11-14T00:00:00.000Z", "dateTimeGMT": "2018-11-14T00:00:00.000Z", "team-1": "Australia Women", "team-2": "New Zealand Women", "type": "WomensT20I", "squad": true, "matchStarted": false}, {"unique_id": 1150543, "date": "2018-11-14T00:00:00.000Z", "dateTimeGMT": "2018-11-14T20:00:00.000Z", "team-1": "Bangladesh Women", "team-2": "Sri Lanka Women", "type": "WomensT20I", "squad": true, "matchStarted": false}, {"unique_id": 1150544, "date": "2018-11-15T00:00:00.000Z", "dateTimeGMT": "2018-11-15T00:00:00.000Z", "team-1": "West Indies Women", "team-2": "South Africa Women", "type": "WomensT20I", "squad": true, "matchStarted": false}, {"unique_id": 1150545, "date": "2018-11-15T00:00:00.000Z", "dateTimeGMT": "2018-11-15T15:00:00.000Z", "team-1": "India Women", "team-2": "Ireland Women", "type": "WomensT20I", "squad": true, "matchStarted": false}, {"unique_id": 1150546, "date": "2018-11-15T00:00:00.000Z", "dateTimeGMT": "2018-11-15T20:00:00.000Z", "team-1": "New Zealand Women", "team-2": "Pakistan Women", "type": "WomensT20I", "squad": true, "matchStarted": false}, {"unique_id": 1150547, "date": "2018-11-16T00:00:00.000Z", "dateTimeGMT": "2018-11-16T20:00:00.000Z", "team-1": "England Women", "team-2": "South Africa Women", "type": "WomensT20I", "squad": true, "matchStarted": false}, {"unique_id": 1157381, "date": "2018-11-16T00:00:00.000Z", "dateTimeGMT": "2018-11-16T06:00:00.000Z", "team-1": "New Zealand", "team-2": "Pakistan", "type": "Test", "squad": true, "matchStarted": false}, {"unique_id": 1150548, "date": "2018-11-17T00:00:00.000Z", "dateTimeGMT": "2018-11-17T00:00:00.000Z", "team-1": "West Indies Women", "team-2": "Sri Lanka Women", "type": "WomensT20I", "squad": true, "matchStarted": false}, {"unique_id": 1150549, "date": "2018-11-17T00:00:00.000Z", "dateTimeGMT": "2018-11-17T15:00:00.000Z", "team-1": "Australia Women", "team-2": "India Women", "type": "WomensT20I", "squad": true, "matchStarted": false}, {"unique_id": 1150550, "date": "2018-11-17T00:00:00.000Z", "dateTimeGMT": "2018-11-17T20:00:00.000Z", "team-1": "Ireland Women", "team-2": "New Zealand Women", "type": "WomensT20I", "squad": true, "matchStarted": false}, {"unique_id": 1144989, "date": "2018-11-17T00:00:00.000Z", "dateTimeGMT": "2018-11-17T08:20:00.000Z", "team-1": "Australia", "team-2": "South Africa", "type": "T20I", "squad": true, "matchStarted": false}, {"unique_id": 1150551, "date": "2018-11-18T00:00:00.000Z", "dateTimeGMT": "2018-11-18T20:00:00.000Z", "team-1": "West Indies Women", "team-2": "England Women", "type": "WomensT20I", "squad": true, "matchStarted": false}, {"unique_id": 1150552, "date": "2018-11-19T00:00:00.000Z", "dateTimeGMT": "2018-11-19T00:00:00.000Z", "team-1": "Bangladesh Women", "team-2": "South Africa Women", "type": "WomensT20I", "squad": true, "matchStarted": false}, {"unique_id": 1144990, "date": "2018-11-21T00:00:00.000Z", "dateTimeGMT": "2018-11-21T07:50:00.000Z", "team-1": "Australia", "team-2": "India", "type": "T20I", "squad": true, "matchStarted": false}, {"unique_id": 1150553, "date": "2018-11-22T00:00:00.000Z", "dateTimeGMT": "2018-11-22T20:00:00.000Z", "team-1": "TBA", "team-2": "TBA", "type": "WomensT20I", "squad": false, "matchStarted": false}, {"unique_id": 1140387, "team-2": "England", "team-1": "Sri Lanka", "type": "Test", "date": "2018-11-23T00:00:00.000Z", "dateTimeGMT": "2018-11-23T04:30:00.000Z", "squad": true, "matchStarted": false}, {"unique_id": 1144991, "date": "2018-11-23T00:00:00.000Z", "dateTimeGMT": "2018-11-23T07:50:00.000Z", "team-1": "Australia", "team-2": "India", "type": "T20I", "squad": true, "matchStarted": false}, {"unique_id": 1150554, "date": "2018-11-23T00:00:00.000Z", "dateTimeGMT": "2018-11-23T00:00:00.000Z", "team-1": "TBA", "team-2": "TBA", "type": "WomensT20I", "squad": false, "matchStarted": false}, {"unique_id": 1157382, "date": "2018-11-24T00:00:00.000Z", "dateTimeGMT": "2018-11-24T06:00:00.000Z", "team-1": "New Zealand", "team-2": "Pakistan", "type": "Test", "squad": false, "matchStarted": false}, {"unique_id": 1144992, "date": "2018-11-25T00:00:00.000Z", "dateTimeGMT": "2018-11-25T07:50:00.000Z", "team-1": "Australia", "team-2": "India", "type": "T20I", "squad": false, "matchStarted": false}, {"unique_id": 1150555, "date": "2018-11-25T00:00:00.000Z", "dateTimeGMT": "2018-11-25T00:00:00.000Z", "team-1": "TBA", "team-2": "TBA", "type": "WomensT20I", "squad": false, "matchStarted": false}, {"unique_id": 1157383, "date": "2018-12-03T00:00:00.000Z", "dateTimeGMT": "2018-12-03T06:00:00.000Z", "team-1": "New Zealand", "team-2": "Pakistan", "type": "Test", "squad": false, "matchStarted": false}, {"unique_id": 1144152, "team-2": "Pakistanis", "team-1": "Cricket South Africa Invitation XI", "type": "", "date": "2018-12-19T00:00:00.000Z", "dateTimeGMT": "2018-12-19T08:00:00.000Z", "squad": false, "matchStarted": false}, {"unique_id": 1144153, "team-2": "Pakistan", "team-1": "South Africa", "type": "Test", "date": "2018-12-26T00:00:00.000Z", "dateTimeGMT": "2018-12-26T08:00:00.000Z", "squad": false, "matchStarted": false}, {"unique_id": 1144154, "team-2": "Pakistan", "team-1": "South Africa", "type": "Test", "date": "2019-01-03T00:00:00.000Z", "dateTimeGMT": "2019-01-03T08:30:00.000Z", "squad": false, "matchStarted": false}, {"unique_id": 1144155, "team-2": "Pakistan", "team-1": "South Africa", "type": "Test", "date": "2019-01-11T00:00:00.000Z", "dateTimeGMT": "2019-01-11T08:00:00.000Z", "squad": false, "matchStarted": false}, {"unique_id": 1144156, "team-2": "Pakistan", "team-1": "South Africa", "type": "ODI", "date": "2019-01-19T00:00:00.000Z", "dateTimeGMT": "2019-01-19T11:00:00.000Z", "squad": false, "matchStarted": false}, {"unique_id": 1144157, "team-2": "Pakistan", "team-1": "South Africa", "type": "ODI", "date": "2019-01-22T00:00:00.000Z", "dateTimeGMT": "2019-01-22T11:00:00.000Z", "squad": false, "matchStarted": false}, {"unique_id": 1144158, "team-2": "Pakistan", "team-1": "South Africa", "type": "ODI", "date": "2019-01-25T00:00:00.000Z", "dateTimeGMT": "2019-01-25T11:00:00.000Z", "squad": false, "matchStarted": false}, {"unique_id": 1144159, "team-2": "Pakistan", "team-1": "South Africa", "type": "ODI", "date": "2019-01-27T00:00:00.000Z", "dateTimeGMT": "2019-01-27T08:00:00.000Z", "squad": false, "matchStarted": false}, {"unique_id": 1144160, "team-2": "Pakistan", "team-1": "South Africa", "type": "ODI", "date": "2019-01-30T00:00:00.000Z", "dateTimeGMT": "2019-01-30T11:00:00.000Z", "squad": false, "matchStarted": false}, {"unique_id": 1144161, "team-2": "Pakistan", "team-1": "South Africa", "type": "T20I", "date": "2019-02-01T00:00:00.000Z", "dateTimeGMT": "2019-02-01T16:00:00.000Z", "squad": false, "matchStarted": false}, {"unique_id": 1144162, "team-2": "Pakistan", "team-1": "South Africa", "type": "T20I", "date": "2019-02-03T00:00:00.000Z", "dateTimeGMT": "2019-02-03T12:30:00.000Z", "squad": false, "matchStarted": false}, {"unique_id": 1144163, "team-2": "Pakistan", "team-1": "South Africa", "type": "T20I", "date": "2019-02-06T00:00:00.000Z", "dateTimeGMT": "2019-02-06T16:00:00.000Z", "squad": false, "matchStarted": false}, {"unique_id": 1144982, "team-2": "New Zealand Women", "team-1": "Australia Women", "type": "WomensODI", "date": "2019-02-22T00:00:00.000Z", "dateTimeGMT": "2019-02-22T02:20:00.000Z", "squad": false, "matchStarted": false}, {"unique_id": 1144983, "team-2": "New Zealand Women", "team-1": "Australia Women", "type": "WomensODI", "date": "2019-02-24T00:00:00.000Z", "dateTimeGMT": "2019-02-24T00:50:00.000Z", "squad": false, "matchStarted": false}, {"unique_id": 1144981, "team-2": "New Zealand Women", "team-1": "Australia Governor-General's XI", "type": "", "date": "2019-02-28T00:00:00.000Z", "dateTimeGMT": "2019-02-28T00:00:00.000Z", "squad": false, "matchStarted": false}, {"unique_id": 1144984, "team-2": "New Zealand Women", "team-1": "Australia Women", "type": "WomensODI", "date": "2019-03-03T00:00:00.000Z", "dateTimeGMT": "2019-03-03T00:50:00.000Z", "squad": false, "matchStarted": false}], "v": "1", "ttl": 150, "provider": {"source": "Various", "url": "https://cricapi.com/", "pubDate": "2018-11-08T18:35:31.140Z"}, "creditsLeft": 228}